{
  "Fields":[
    {
      "name":"金蝶组织ID",
      "toField":"kd_org_id",
      "myField":"kd_org_id",
      "from":"mid_org",
      "toType":"int"
    },
    {
      "name":"金蝶组织名字",
      "toField":"kd_org_name",
      "myField":"kd_org_name",
      "from":"mid_org",
      "toType":"varchar"
    },
    {
      "name":"金蝶组织编码",
      "toField":"kd_org_num",
      "myField":"kd_org_num",
      "from":"mid_org",
      "toType":"varchar"
    },
    {
      "name":"创建时间",
      "toField":"gmt_create",
      "myField":"gmt_create",
      "from":"mid_org",
      "toType":"timestamp"
    },
    {
      "name":"修改时间",
      "toField":"gmt_modified",
      "myField":"gmt_modified",
      "from":"mid_org",
      "toType":"timestamp"
    },
    {
      "name":"是否删除",
      "toField":"is_delete",
      "myField":"is_delete",
      "from":"mid_org",
      "toType":"int"
    }
  ]
}